CHANGELOG.md
LICENSE
django_component_kit/__init__.py
django_component_kit/apps.py
django_component_kit/assets.py
django_component_kit/attributes.py
django_component_kit/decorators.py
django_component_kit/nodes.py
django_component_kit/partials.py
django_component_kit/tags.py
django_component_kit/templatetags/__init__.py
django_component_kit/templatetags/components.py
django_component_kit/utils.py
django_component_kit-0.5.1.dist-info/LICENSE
django_component_kit-0.5.1.dist-info/METADATA
django_component_kit-0.5.1.dist-info/WHEEL
django_component_kit-0.5.1.dist-info/RECORD
