Metadata-Version: 2.1
Name: django-component-kit
Version: 0.5.1
Summary: A lightweight library for flexible Django component building, following Django's principles.
Home-page: https://github.com/SaschaKrug/django-component-kit
License: MIT
Keywords: django,component,tag,decorator
Author: Sascha Krug
Requires-Python: >=3.10,<4.0
Classifier: Development Status :: 4 - Beta
Classifier: Environment :: Web Environment
Classifier: Framework :: Django
Classifier: Framework :: Django :: 4.0
Classifier: Framework :: Django :: 4.1
Classifier: Framework :: Django :: 4.2
Classifier: Framework :: Django :: 5.0
Classifier: License :: OSI Approved :: MIT License
Classifier: Operating System :: OS Independent
Classifier: Programming Language :: Python :: 3
Classifier: Programming Language :: Python :: 3.10
Classifier: Programming Language :: Python :: 3.11
Classifier: Programming Language :: Python :: 3.12
Requires-Dist: Django (>=3.2)
Project-URL: Repository, https://github.com/SaschaKrug/django-component-kit
